model_helper/__init__.py
model_helper/main.py
model_helper/PyALE/_ALE_generic.py
model_helper/PyALE/__init__.py
model_helper/PyALE/_src/ALE_1D.py
model_helper/PyALE/_src/ALE_2D.py
model_helper/PyALE/_src/__init__.py
model_helper/PyALE/_src/lib.py
model_helper/clean/__init__.py
model_helper/clean/base.py
model_helper/clean/dates.py
model_helper/clean/encode_categorical.py
model_helper/clean/fill_missing.py
model_helper/clean/main.py
model_helper/clean/shrink.py
model_helper/clean/split.py
model_helper/clustering/__init__.py
model_helper/clustering/clustering.py
model_helper/explain/__init__.py
model_helper/explain/ale.py
model_helper/explain/bin.py
model_helper/explain/ebm.py
model_helper/explain/importance.py
model_helper/explain/main.py
model_helper/explain/one_way.py
model_helper/explain/pdp.py
model_helper/explain/sensitivity.py
model_helper/explain/shap.py
model_helper/metrics/__init__.py
model_helper/metrics/classification.py
model_helper/metrics/regression.py
model_helper/models/__init__.py
model_helper/models/ebm.py
model_helper/models/random_forest.py
model_helper/models/xgboost.py
model_helper/utils/__init__.py
model_helper/utils/colours.py
model_helper/utils/data.py
model_helper/utils/logic.py
model_helper/utils/plot.py
modelflow/__init__.py
modelflow/main.py
modelflow/PyALE/_ALE_generic.py
modelflow/PyALE/__init__.py
modelflow/PyALE/_src/ALE_1D.py
modelflow/PyALE/_src/ALE_2D.py
modelflow/PyALE/_src/__init__.py
modelflow/PyALE/_src/lib.py
modelflow/clean/__init__.py
modelflow/clean/base.py
modelflow/clean/dates.py
modelflow/clean/encode_categorical.py
modelflow/clean/fill_missing.py
modelflow/clean/main.py
modelflow/clean/shrink.py
modelflow/clean/split.py
modelflow/clustering/__init__.py
modelflow/clustering/clustering.py
modelflow/explain/__init__.py
modelflow/explain/ale.py
modelflow/explain/bin.py
modelflow/explain/ebm.py
modelflow/explain/importance.py
modelflow/explain/main.py
modelflow/explain/one_way.py
modelflow/explain/pdp.py
modelflow-0.0.16.dist-info/METADATA
modelflow-0.0.16.dist-info/WHEEL
modelflow-0.0.16.dist-info/top_level.txt
modelflow-0.0.16.dist-info/RECORD
